vfab/__init__.py
vfab/backup.py
vfab/checklist.py
vfab/codes.py
vfab/config.py
vfab/db.py
vfab/detection.py
vfab/estimation.py
vfab/fsm.py
vfab/hooks.py
vfab/init.py
vfab/logging.py
vfab/models.py
vfab/paper.py
vfab/planner.py
vfab/plob.py
vfab/plotting.py
vfab/presets.py
vfab/progress.py
vfab/recovery.py
vfab/stats.py
vfab/utils.py
vfab/uv.lock
vfab/vpype.py
vfab/cli/__init__.py
vfab/cli/__main__.py
vfab/cli/commands.py
vfab/cli/common.py
vfab/cli/core.py
vfab/cli/daemon.py
vfab/cli/interactive.py
vfab/cli/monitor.py
vfab/cli/restart.py
vfab/cli/resume.py
vfab/cli/add/__init__.py
vfab/cli/check/__init__.py
vfab/cli/check/camera.py
vfab/cli/check/job.py
vfab/cli/check/ready.py
vfab/cli/check/self.py
vfab/cli/check/servo.py
vfab/cli/check/timing.py
vfab/cli/guard/__init__.py
vfab/cli/guard/check.py
vfab/cli/guard/list.py
vfab/cli/guard/validate.py
vfab/cli/info/__init__.py
vfab/cli/info/job.py
vfab/cli/info/output.py
vfab/cli/info/paths.py
vfab/cli/info/queue.py
vfab/cli/info/session.py
vfab/cli/info/system.py
vfab/cli/info/utils.py
vfab/cli/list/__init__.py
vfab/cli/list/jobs.py
vfab/cli/list/paper_management.py
vfab/cli/list/pen_management.py
vfab/cli/list/presets.py
vfab/cli/list/setup_wizard.py
vfab/cli/remove/__init__.py
vfab/cli/stats/__init__.py
vfab/cli/stats/jobs.py
vfab/cli/stats/performance.py
vfab/cli/stats/summary.py
vfab/cli/system/__init__.py
vfab/cli/system/export.py
vfab/cli/system/import_cmd.py
vfab/cli/system/logs.py
vfab/cli/system/stats/__init__.py
vfab/config/config.yaml
vfab/config/vpype-presets.yaml
vfab/drivers/__init__.py
vfab/drivers/axidraw.py
vfab/drivers/postgresql.py
vfab/drivers/sqlite.py
vfab/guards/__init__.py
vfab/guards/base.py
vfab/guards/job_guards.py
vfab/guards/manager.py
vfab/guards/system_guards.py
vfab/multipen/__init__.py
vfab/multipen/axidraw_integration.py
vfab/multipen/pen_mapping.py
vfab/multipen/svg_detector.py
vfab/multipen/types.py
vfab/testing/__init__.py
vfab/testing/models.py
vfab/testing/reporter.py
vfab-0.9.0.dist-info/licenses/LICENSE
vfab-0.9.0.dist-info/METADATA
vfab-0.9.0.dist-info/WHEEL
vfab-0.9.0.dist-info/entry_points.txt
vfab-0.9.0.dist-info/top_level.txt
vfab-0.9.0.dist-info/RECORD
