Metadata-Version: 2.4
Name: vfab
Version: 0.9.0
Summary: vfab: FSM plotter manager (headless-first) with vpype + per-session recording
License-Expression: MIT
Requires-Python: >=3.13
License-File: LICENSE
Requires-Dist: typer>=0.12.3
Requires-Dist: pydantic>=2.9
Requires-Dist: pyyaml>=6.0.2
Requires-Dist: sqlalchemy>=2.0.36
Requires-Dist: alembic>=1.13.2
Requires-Dist: rich>=13.0.0
Requires-Dist: jinja2>=3.1.0
Requires-Dist: psutil>=5.9.0
Requires-Dist: click>=8.0.0
Requires-Dist: platformdirs>=4.0.0
Requires-Dist: defusedxml>=0.7.1
Requires-Dist: fastapi>=0.104.0
Requires-Dist: websockets>=12.0
Requires-Dist: uvicorn[standard]>=0.24.0
Provides-Extra: vpype
Requires-Dist: vpype>=1.14.0; extra == "vpype"
Provides-Extra: axidraw
Provides-Extra: dev
Requires-Dist: pytest>=8.3.2; extra == "dev"
Requires-Dist: pre-commit>=3.8.0; extra == "dev"
Requires-Dist: ruff>=0.6.8; extra == "dev"
Requires-Dist: black>=24.10.0; extra == "dev"
Dynamic: license-file
